dagster_scaleway/__init__.py
dagster_scaleway/cli.py
dagster_scaleway/serverless_job_context.py
dagster_scaleway/serverless_job_launcher.py
dagster_scaleway-0.1.3.dist-info/METADATA
dagster_scaleway-0.1.3.dist-info/WHEEL
dagster_scaleway-0.1.3.dist-info/entry_points.txt
dagster_scaleway-0.1.3.dist-info/RECORD
