Metadata-Version: 2.1
Name: dagster-scaleway
Version: 0.1.3
Summary: 
License: Apache-2.0
Author: Andy Méry
Author-email: amery@scaleway.com
Requires-Python: >=3.11,<4.0
Classifier: License :: OSI Approved :: Apache Software License
Classifier: Programming Language :: Python :: 3
Classifier: Programming Language :: Python :: 3.11
Classifier: Programming Language :: Python :: 3.12
Requires-Dist: dagster (>=1.6.0,<2.0.0)
Requires-Dist: scaleway (>=2.1.0,<3.0.0)
